AUTHORS.rst
CHANGES.rst
LICENSE.txt
MANIFEST.in
README.rst
TODO.rst
setup.py
django_mustachejs.egg-info/PKG-INFO
django_mustachejs.egg-info/SOURCES.txt
django_mustachejs.egg-info/dependency_links.txt
django_mustachejs.egg-info/not-zip-safe
django_mustachejs.egg-info/top_level.txt
mustachejs/__init__.py
mustachejs/conf.py
mustachejs/finders.py
mustachejs/loading.py
mustachejs/models.py
mustachejs/preprocessors.py
mustachejs/management/__init__.py
mustachejs/management/commands/__init__.py
mustachejs/management/commands/makemessages.py
mustachejs/static/mustache/js/django.mustache.js
mustachejs/static/mustache/js/mustache-0.3.0.js
mustachejs/static/mustache/js/mustache-0.4.0-dev.js
mustachejs/templatetags/__init__.py
mustachejs/templatetags/base.py
mustachejs/templatetags/dustjs.py
mustachejs/templatetags/mustacheich.py
mustachejs/templatetags/mustachejs.py
mustachejs/templatetags/mustacheraw.py
mustachejs/tests/__init__.py
mustachejs/tests/mockfinders.py
mustachejs/tests/mockpreprocessors.py
mustachejs/tests/test_finders.py
mustachejs/tests/test_loading.py
mustachejs/tests/test_makemessages.py
mustachejs/tests/test_translation.py
mustachejs/tests/test_ttag.py
mustachejs/tests/utils.py