Metadata-Version: 1.1
Name: django-mustachejs
Version: 0.8.3
Summary: A Django template tag for embedding Mustache.js templates safely.
Home-page: https://github.com/mjumbewu/django-mustachejs/
Author: Mjumbe Wawatu Ukweli
Author-email: mjumbewu@gmail.com
License: UNKNOWN
Platform: UNKNOWN
Classifier: Development Status :: 4 - Beta
Classifier: Environment :: Web Environment
Classifier: Intended Audience :: Developers
Classifier: License :: OSI Approved :: BSD License
Classifier: Operating System :: OS Independent
Classifier: Programming Language :: Python
Classifier: Programming Language :: Python :: 2
Classifier: Programming Language :: Python :: 2.6
Classifier: Programming Language :: Python :: 2.7
Classifier: Framework :: Django
